randomize/__init__.py
randomize/plugin.py
randomize-0.14.dist-info/DESCRIPTION.rst
randomize-0.14.dist-info/METADATA
randomize-0.14.dist-info/RECORD
randomize-0.14.dist-info/WHEEL
randomize-0.14.dist-info/entry_points.txt
randomize-0.14.dist-info/metadata.json
randomize-0.14.dist-info/top_level.txt
